{"monument":[
    {
        "title": "Limestone funerary monument of a woman",
        "country": "Italy",
        "culture": "Roman, Cypriot",
        "image": "https://images.metmuseum.org/CRDImages/gr/original/DP274535.jpg"
    },
    {
        "title": "Model for a Proposed Monument to Commemorate the Invention of the Balloon",
        "country": "France",
        "culture": "",
        "image": "https://images.metmuseum.org/CRDImages/es/original/DP248127.jpg"
    },
    {
        "title": "Design for a Wall Monument",
        "country": "Italy",
        "culture": "",
        "image": "https://images.metmuseum.org/CRDImages/rl/original/DP324211.jpg"
    },
    {
        "title": "Final Study for the Monument to Balzac",
        "country": "France",
        "culture": "",
        "image": "https://images.metmuseum.org/CRDImages/es/original/DP-13618-017.jpg"
    },
    {
        "title": "Fragment of a marble relief from a funerary monument",
        "country": "Greece",
        "culture": "Greece, Attic",
        "image": "https://images.metmuseum.org/CRDImages/gr/original/DT259949.jpg"
    },
    {
        "title": "Study for the Equestrian Monument to Francesco Sforza",
        "country": "Italy",
        "culture": "",
        "image": "https://images.metmuseum.org/CRDImages/rl/original/DP324215.jpg"
    },
    {
        "title": "Model for a Papal monument",
        "country": "Belgium",
        "culture": "",
        "image": "https://images.metmuseum.org/CRDImages/es/original/231613.jpg"
    },
    {
        "title": "Limestone funerary monument of a beardless man",
        "country": "Italy",
        "culture": "Roman, Cypriot",
        "image": "https://images.metmuseum.org/CRDImages/gr/original/DT241322.jpg"
    },
    {
        "title": "Limestone funerary monument with a seated woman",
        "country": "Cypriot",
        "culture": "Cypriot",
        "image": "https://images.metmuseum.org/CRDImages/gr/original/DP229731.jpg"
    },
    {
        "title": "Marble akroterion of the grave monument of Timotheos and Nikon",
        "country": "Greece",
        "culture": "Greece, Attic",
        "image": "https://images.metmuseum.org/CRDImages/gr/original/GR97.jpg"
    },
    {
        "title": "Sepulchral Monument of Ermengol X, Count of Urgell",
        "country": "Spain",
        "culture": "Spain",
        "image": "https://images.metmuseum.org/CRDImages/cl/original/DP148623.jpg"
    },
    {
        "title": "Front of a limestone block from the stepped base of a funerary monument",
        "country": "",
        "culture": "Greece, Attic",
        "image": "https://images.metmuseum.org/CRDImages/gr/original/DT361131.jpg"
    },
    {
        "title": "Grave Monument",
        "country": "Turkey",
        "culture": "Byzantine",
        "image": "https://images.metmuseum.org/CRDImages/md/original/sf10-176-38s1.jpg"
    },
    {
        "title": "Grave Monument",
        "country": "Turkey",
        "culture": "Byzantine",
        "image": "https://images.metmuseum.org/CRDImages/md/original/sf10-176-39s1.jpg"
    },
    {
        "title": "Wall Monument",
        "country": "Italy",
        "culture": "",
        "image": "https://images.metmuseum.org/CRDImages/dp/original/DP801911.jpg"
    },
    {
        "title": "Corbel from the Double Sepulchral Monument of Don Àlvar Rodrigo de Cabrera, Count of Urgell and Viscount of Ager and his wife Cecilia of Foix",
        "country": "Spain",
        "culture": "Spain",
        "image": "https://images.metmuseum.org/CRDImages/cl/original/cdi48-140-4.jpg"
    },
    {
        "title": "Corbel from the Double Sepulchral Monument of Don Àlvar Rodrigo de Cabrera, Count of Urgell and His Wife Cecília of Foix",
        "country": "Spain",
        "culture": "Spain",
        "image": "https://images.metmuseum.org/CRDImages/cl/original/cdi48-140-3.jpg"
    },
    {
        "title": "Les Adieux, from Le Monument du Costume",
        "country": "",
        "culture": "",
        "image": "https://images.metmuseum.org/CRDImages/dp/original/DT201325.jpg"
    },
    {
        "title": "The Morning Toilet (La Petite Toilette), from Le Monument du Costume",
        "country": "Italy",
        "culture": "",
        "image": "https://images.metmuseum.org/CRDImages/dp/original/DT232068.jpg"
    },
    {
        "title": "Studies of a monument",
        "country": "Germany",
        "culture": "",
        "image": "https://images.metmuseum.org/CRDImages/dp/original/DP804512.jpg"
    },
    {
        "title": "La Grande Toilette (The Patroness), from Le Monument du Costume",
        "country": "France",
        "culture": "",
        "image": "https://images.metmuseum.org/CRDImages/dp/original/DP-17606-001.jpg"
    },
    {
        "title": "Design for a Monument",
        "country": "Italy",
        "culture": "",
        "image": "https://images.metmuseum.org/CRDImages/dp/original/DP801331.jpg"
    },
    {
        "title": "Sketch for Wall Monument",
        "country": "Italy",
        "culture": "",
        "image": "https://images.metmuseum.org/CRDImages/dp/original/DP801930.jpg"
    },
    {
        "title": "Sketch for Wall Monument",
        "country": "Italy",
        "culture": "",
        "image": "https://images.metmuseum.org/CRDImages/dp/original/DP801899.jpg"
    },
    {
        "title": "Design for Monument",
        "country": "France",
        "culture": "",
        "image": "https://images.metmuseum.org/CRDImages/dp/original/DP808746.jpg"
    },
    {
        "title": "Design for a  Monument",
        "country": "France",
        "culture": "",
        "image": "https://images.metmuseum.org/CRDImages/dp/original/DP808119.jpg"
    },
    {
        "title": "Soldiers Around a Monument",
        "country": "Italy",
        "culture": "",
        "image": "https://images.metmuseum.org/CRDImages/rl/original/DT3206.jpg"
    },
    {
        "title": "The Martyrs' Monument",
        "country": "Britain",
        "culture": "",
        "image": "https://images.metmuseum.org/CRDImages/ph/original/DP147250.jpg"
    },
    {
        "title": "Design for a monument",
        "country": "France",
        "culture": "",
        "image": "https://images.metmuseum.org/CRDImages/dp/original/DP808593.jpg"
    },
    {
        "title": "Spired Gothic Monument",
        "country": "",
        "culture": "",
        "image": "https://images.metmuseum.org/CRDImages/dp/original/DP-18336-001.jpg"
    },
    {
        "title": "Tomb Monument with Skeletons",
        "country": "Italy",
        "culture": "",
        "image": "https://images.metmuseum.org/CRDImages/dp/original/DP802563.jpg"
    },
    {
        "title": "Design for Tomb Monument",
        "country": "",
        "culture": "",
        "image": "https://images.metmuseum.org/CRDImages/dp/original/DP808796.jpg"
    },
    {
        "title": "Decoration for a Monument",
        "country": "France",
        "culture": "",
        "image": "https://images.metmuseum.org/CRDImages/dp/original/DP808745.jpg"
    },
    {
        "title": "Monument of Richard Jervoice, 1563",
        "country": "Britain",
        "culture": "",
        "image": "https://images.metmuseum.org/CRDImages/dp/original/DP806357.jpg"
    },
    {
        "title": "Monument of Eudo de Arsie",
        "country": "",
        "culture": "",
        "image": "https://images.metmuseum.org/CRDImages/dp/original/DP829118.jpg"
    },
    {
        "title": "Scott Monument before Completion, Edinburgh",
        "country": "Britain",
        "culture": "",
        "image": "https://images.metmuseum.org/CRDImages/ph/original/DP148634.jpg"
    },
    {
        "title": "Design for a Wall Monument",
        "country": "France",
        "culture": "",
        "image": "https://images.metmuseum.org/CRDImages/dp/original/DP805583.jpg"
    },
    {
        "title": "Rustic Landscape with Stone Monument",
        "country": "France",
        "culture": "",
        "image": "https://images.metmuseum.org/CRDImages/dp/original/53.523.46.jpg"
    },
    {
        "title": "Design for a Funerary Monument",
        "country": "Italy",
        "culture": "",
        "image": "https://images.metmuseum.org/CRDImages/dp/original/DP811552.jpg"
    },
    {
        "title": "Design for a Monument (recto)",
        "country": "France",
        "culture": "",
        "image": "https://images.metmuseum.org/CRDImages/dp/original/DP812363.jpg"
    },
    {
        "title": "Edinburgh. The Scott Monument",
        "country": "Britain, Scottish",
        "culture": "",
        "image": "https://images.metmuseum.org/CRDImages/ph/original/DP140464.jpg"
    },
    {
        "title": "Design for a Funerary Monument",
        "country": "Germany",
        "culture": "",
        "image": "https://images.metmuseum.org/CRDImages/dp/original/DP803580.jpg"
    },
    {
        "title": "Landscape with Road and Monument",
        "country": "France",
        "culture": "",
        "image": "https://images.metmuseum.org/CRDImages/rl/original/SF-1975-1-629.jpg"
    },
    {
        "title": "Edinburgh.  The Scott Monument",
        "country": "Britain, Scottish",
        "culture": "",
        "image": "https://images.metmuseum.org/CRDImages/ph/original/DP140463.jpg"
    },
    {
        "title": "Grave Monument Design (Two elevations)",
        "country": "",
        "culture": "",
        "image": "https://images.metmuseum.org/CRDImages/dp/original/DP885389.jpg"
    },
    {
        "title": "Design for a Funeral Monument",
        "country": "",
        "culture": "Italy, Lombard",
        "image": "https://images.metmuseum.org/CRDImages/rl/original/DP-13665-024.jpg"
    },
    {
        "title": "Project for a Public Monument",
        "country": "France",
        "culture": "",
        "image": "https://images.metmuseum.org/CRDImages/dp/original/DP836563.jpg"
    },
    {
        "title": "Projected Monument on Mt. Cenis",
        "country": "France",
        "culture": "",
        "image": "https://images.metmuseum.org/CRDImages/es/original/30703.jpg"
    },
    {
        "title": "Monumental Head of Buddha",
        "country": "Pakistan",
        "culture": "Pakistan (ancient region of Gandhara) or Afghanistan",
        "image": "https://images.metmuseum.org/CRDImages/as/original/264797_1985.388.jpg"
    },
    {
        "title": "View of a Funerary Monument and Crypt",
        "country": "France",
        "culture": "",
        "image": "https://images.metmuseum.org/CRDImages/dp/original/DP817846.jpg"
    },
    {
        "title": "Design for a Monument with Minerva?",
        "country": "Spanish",
        "culture": "",
        "image": "https://images.metmuseum.org/CRDImages/dp/original/DP800301.jpg"
    },
    {
        "title": "Pyramid monument for J.B. van Bree",
        "country": "Netherlands",
        "culture": "",
        "image": "https://images.metmuseum.org/CRDImages/dp/original/DP800921.jpg"
    },
    {
        "title": "Monument to Sir Walter Scott, Bart.",
        "country": "Britain",
        "culture": "",
        "image": "https://images.metmuseum.org/CRDImages/dp/original/DP805072.jpg"
    },
    {
        "title": "Design of an Architectural Monument (Tomb?).",
        "country": "Italy",
        "culture": "",
        "image": "https://images.metmuseum.org/CRDImages/dp/original/DP804070.jpg"
    },
    {
        "title": "Design for a Double Heart Monument",
        "country": "France",
        "culture": "",
        "image": "https://images.metmuseum.org/CRDImages/dp/original/DP812283.jpg"
    },
    {
        "title": "Grave Monument with Cross, No. 745",
        "country": "",
        "culture": "",
        "image": "https://images.metmuseum.org/CRDImages/dp/original/DP885523.jpg"
    },
    {
        "title": "Designs for a Funerary Monument with Stairs (Recto). Various Funerary Monument Designs (Verso).",
        "country": "Italy",
        "culture": "",
        "image": "https://images.metmuseum.org/CRDImages/dp/original/DP809745.jpg"
    },
    {
        "title": "Sketch for Figure on Whistler Monument",
        "country": "France",
        "culture": "",
        "image": "https://images.metmuseum.org/CRDImages/dp/original/DP808100.jpg"
    },
    {
        "title": "Pompeii, Pompey’s Lane, Tomb Monument of Mamia",
        "country": "France",
        "culture": "",
        "image": "https://images.metmuseum.org/CRDImages/ph/original/DP319714.jpg"
    },
    {
        "title": "Design for a Tomb or Wall Monument",
        "country": "Italy",
        "culture": "",
        "image": "https://images.metmuseum.org/CRDImages/dp/original/DP802682.jpg"
    },
    {
        "title": "The Monument to Alexander Hamilton at Weehawken",
        "country": "",
        "culture": "",
        "image": "https://images.metmuseum.org/CRDImages/ad/original/ap42.95.6.jpg"
    },
    {
        "title": "Design after the monument of Leonardo Loredano",
        "country": "",
        "culture": "",
        "image": "https://images.metmuseum.org/CRDImages/dp/original/DP885508.jpg"
    },
    {
        "title": "Design for a Sculpture or Monument",
        "country": "France",
        "culture": "",
        "image": "https://images.metmuseum.org/CRDImages/dp/original/DP812366.jpg"
    },
    {
        "title": "Three Designs for a Funerary Monument or Epitaph",
        "country": "France",
        "culture": "",
        "image": "https://images.metmuseum.org/CRDImages/dp/original/DP823927.jpg"
    },
    {
        "title": "Design for a Funeral Monument (Preparatory Drawing for a Print)",
        "country": "Germany",
        "culture": "",
        "image": "https://images.metmuseum.org/CRDImages/dp/original/DP874836.jpg"
    },
    {
        "title": "Design for a sepulchral monument with an allegory of Time; verso: Design for a sepulchral monument",
        "country": "Belgium",
        "culture": "",
        "image": "https://images.metmuseum.org/CRDImages/dp/original/DP808637.jpg"
    },
    {
        "title": "Left Half Design for Wall Monument with Escutcheon Motif",
        "country": "Italy",
        "culture": "",
        "image": "https://images.metmuseum.org/CRDImages/dp/original/DP802689.jpg"
    },
    {
        "title": "Design for a Monument to the First Punjab War, 1845-46",
        "country": "",
        "culture": "",
        "image": "https://images.metmuseum.org/CRDImages/dp/original/DP-12430-001.jpg"
    },
    {
        "title": "Limestone funerary monument with four figures",
        "country": "",
        "culture": "Cypriot",
        "image": "https://images.metmuseum.org/CRDImages/gr/original/DP218561.jpg"
    },
    {
        "title": "Tomb Monument with Crucifix and Coat of Arms",
        "country": "Italy",
        "culture": "",
        "image": "https://images.metmuseum.org/CRDImages/dp/original/DP802564.jpg"
    },
    {
        "title": "Project for the Monument de la Montagne, Orléans",
        "country": "France",
        "culture": "",
        "image": "https://images.metmuseum.org/CRDImages/dp/original/DP810339.jpg"
    },
    {
        "title": "Design for a sepulchral monument; verso: Design for a monument",
        "country": "Belgium",
        "culture": "",
        "image": "https://images.metmuseum.org/CRDImages/dp/original/DP808645.jpg"
    },
    {
        "title": "Design for a Monument to a Military Leader",
        "country": "France",
        "culture": "",
        "image": "https://images.metmuseum.org/CRDImages/dp/original/DP812008.jpg"
    },
    {
        "title": "Proposed Monument to John L. Carey of Baltimore",
        "country": "American",
        "culture": "",
        "image": "https://images.metmuseum.org/CRDImages/dp/original/DP805113.jpg"
    },
    {
        "title": "Design for a sepulchral monument; verso: Design for a sepulchral monument",
        "country": "Belgium",
        "culture": "",
        "image": "https://images.metmuseum.org/CRDImages/dp/original/DP808626.jpg"
    },
    {
        "title": "Design for a Funerary Monument or Epitaph with Mourning Figures",
        "country": "Italy",
        "culture": "",
        "image": "https://images.metmuseum.org/CRDImages/dp/original/DP803192.jpg"
    },
    {
        "title": "Design for a sepulchral monument with an allegory of Time",
        "country": "Belgium",
        "culture": "",
        "image": "https://images.metmuseum.org/CRDImages/dp/original/DP808630.jpg"
    },
    {
        "title": "Monument for Sir Joshua Reynolds (for Carlton-House Magazine)",
        "country": "",
        "culture": "",
        "image": "https://images.metmuseum.org/CRDImages/dp/original/DP886224.jpg"
    },
    {
        "title": "Design for a Catafalque or a Tomb Monument",
        "country": "Italy",
        "culture": "",
        "image": "https://images.metmuseum.org/CRDImages/dp/original/DP803649.jpg"
    },
    {
        "title": "Study for a Monument to a Princely Figure",
        "country": "France",
        "culture": "",
        "image": "https://images.metmuseum.org/CRDImages/ep/original/DP312851.jpg"
    },
    {
        "title": "Right Half of Wall Monument Design with Urn Above",
        "country": "Italy",
        "culture": "",
        "image": "https://images.metmuseum.org/CRDImages/dp/original/DP802690.jpg"
    },
    {
        "title": "Temple Monument in a Park on a Lake",
        "country": "Germany",
        "culture": "",
        "image": "https://images.metmuseum.org/CRDImages/dp/original/DP820714.jpg"
    },
    {
        "title": "Royal Portugese Funeral Monument (possibly part of a funeral book)",
        "country": "",
        "culture": "",
        "image": "https://images.metmuseum.org/CRDImages/dp/original/DP876494.jpg"
    },
    {
        "title": "Design for a sepulchral monument; verso: Design for a sepulchral monument",
        "country": "Belgium",
        "culture": "",
        "image": "https://images.metmuseum.org/CRDImages/dp/original/DP808635.jpg"
    },
    {
        "title": "Philosophy Run Mad or a Stupendous Monument of Human Wisdom",
        "country": "",
        "culture": "",
        "image": "https://images.metmuseum.org/CRDImages/dp/original/DP872076.jpg"
    },
    {
        "title": "Sheet with Various Designs for Tables and a Funerary Monument",
        "country": "Italy",
        "culture": "",
        "image": "https://images.metmuseum.org/CRDImages/dp/original/DP809766.jpg"
    },
    {
        "title": "Family Gathered Before a Monument in a Landscape with a Waterfall",
        "country": "Switzerland",
        "culture": "",
        "image": "https://images.metmuseum.org/CRDImages/dp/original/DP800629.jpg"
    },
    {
        "title": "Monument to Cecco di Sangro in the Sansevero Chapel, Naples",
        "country": "",
        "culture": "",
        "image": "https://images.metmuseum.org/CRDImages/dp/original/DP885725.jpg"
    },
    {
        "title": "Project for the Monument de la Montagne, Orléans",
        "country": "France",
        "culture": "",
        "image": "https://images.metmuseum.org/CRDImages/dp/original/DP810338.jpg"
    },
    {
        "title": "Design for a sepulchral monument with two figures",
        "country": "Belgium",
        "culture": "",
        "image": "https://images.metmuseum.org/CRDImages/dp/original/DP808634.jpg"
    },
    {
        "title": "Design for a sepulchral monument with a portrait bust",
        "country": "Belgium",
        "culture": "",
        "image": "https://images.metmuseum.org/CRDImages/dp/original/DP808658.jpg"
    },
    {
        "title": "Reconstruction of the Monument to Septimius Severus (above), View of the Ruins (below)",
        "country": "Netherlands",
        "culture": "",
        "image": "https://images.metmuseum.org/CRDImages/dp/original/DP800342.jpg"
    },
    {
        "title": "Design for Wall Decoration with a Funeral Monument Decorated with Columns and Putti Holding Garlands.",
        "country": "Italy",
        "culture": "",
        "image": "https://images.metmuseum.org/CRDImages/dp/original/DP802116.jpg"
    },
    {
        "title": "The Cooke Monument in St. Paul's Churchyard (from Scenes of Old New York)",
        "country": "American",
        "culture": "",
        "image": "https://images.metmuseum.org/CRDImages/dp/original/DP818548.jpg"
    },
    {
        "title": "Funerary Monument with Two Male Figures (Santa Maria del Popolo, Cappella Chigi, Rome)",
        "country": "Italy",
        "culture": "",
        "image": "https://images.metmuseum.org/CRDImages/dp/original/DP803037.jpg"
    },
    {
        "title": "A Design for a Monument Dedicated to the Memory of Mr. Henderson",
        "country": "",
        "culture": "",
        "image": "https://images.metmuseum.org/CRDImages/dp/original/DP860162.jpg"
    },
    {
        "title": "Cross-Section and Elevation of the Funeral Monument for General François Séverin Marceau (1769-1796)",
        "country": "France",
        "culture": "",
        "image": "https://images.metmuseum.org/CRDImages/dp/original/DP812519.jpg"
    },
    {
        "title": "Design for a Monument of the Victory of Waterloo (recto); Portico with Corinthian Columns (verso)",
        "country": "Germany",
        "culture": "",
        "image": "https://images.metmuseum.org/CRDImages/dp/original/DP819697.jpg"
    },
    {
        "title": "Stage design: piazza with a building, an obelisk, and a monument. Building and monument with numbers referring to inscription below.",
        "country": "Italy",
        "culture": "",
        "image": "https://images.metmuseum.org/CRDImages/dp/original/DP803654.jpg"
    },
    {
        "title": "Architecture arabe : ou, Monuments du Kaire, mesurés et dessinés, de 1818 à 1826",
        "country": "",
        "culture": "",
        "image": "https://images.metmuseum.org/CRDImages/li/original/b1086151_001.jpg"
    },
    {
        "title": "Funeral monument to Charles V, Duke of Lorraine, frontispiece to 'Les Actions glorieuses de S.A.S. Charles Duc de Lorraine'",
        "country": "",
        "culture": "",
        "image": "https://images.metmuseum.org/CRDImages/dp/original/DP855532.jpg"
    },
    {
        "title": "Design for a Sepulchral Monument Divided in Two Parts with Bas Relief Surmounted by Statues and Foliate Decoration Below.",
        "country": "Italy",
        "culture": "",
        "image": "https://images.metmuseum.org/CRDImages/dp/original/DP809180.jpg"
    },
    {
        "title": "Designs for Archways and Baldachins with Caryatids and Coats of Arms (Recto). Design for a Monument with Statues of Prudence and Fortitude (Verso).",
        "country": "Italy",
        "culture": "",
        "image": "https://images.metmuseum.org/CRDImages/dp/original/DP809743.jpg"
    },
    {
        "title": "Partial View of a Monument [Mercurii Templum] from the series 'Ruinarum variarum fabricarum delineationes pictoribus caeterisque id genus artificibus multum utiles'",
        "country": "Netherlandish",
        "culture": "",
        "image": "https://images.metmuseum.org/CRDImages/dp/original/DP823074.jpg"
    },
    {
        "title": "Facade of a triumphal monument with three scenes depicting deeds of Pope Clement VIII, a temporary decoration for the entry of Pope Clement VIII in Bologna in 1598",
        "country": "Italy",
        "culture": "",
        "image": "https://images.metmuseum.org/CRDImages/dp/original/DP837831.jpg"
    },
    {
        "title": "Frontispiece: a monument decorated with the Medici coat of arms at top in center, flames at top to either side, a hooded figure on right side of monument with a weasel below, a figure to left side wearing a papal crown, a scene of a monk chasing away demons with a cross on base of monument, from 'Frontispiece and four scenes from the life of Saint John Gualbert' (Frontispice et quatre vignettes pour une vie de Saint Jean Gualbert)",
        "country": "Italy",
        "culture": "",
        "image": "https://images.metmuseum.org/CRDImages/dp/original/DP827805.jpg"
    },
    {
        "title": "Plate 1: a monument with statues and a coat of arms in the center, a draughstman on the ground beneath a tree to right, two groups of lovers to left in the background, from 'Various landscapes' (Divers paysages)",
        "country": "Italy",
        "culture": "",
        "image": "https://images.metmuseum.org/CRDImages/dp/original/DP827792.jpg"
    },
    {
        "title": "Plate 4: remains of a classical monument to right surmounted by a mask and tablet, a figure sitting on the porch, four figures on a staircase to left, four milestones below, from 'Les soirées de Rome'",
        "country": "France",
        "culture": "",
        "image": "https://images.metmuseum.org/CRDImages/dp/original/DP829179.jpg"
    },
    {
        "title": "Plate 4: a Corinthian capital on the ground at left, a monument with figures in low relief at left in the middleground, various animals and two shepherds at right, from 'Roman landscapes and ruins' (Paysages et ruines de Rome)",
        "country": "Italy",
        "culture": "",
        "image": "https://images.metmuseum.org/CRDImages/dp/original/DP817975.jpg"
    },
    {
        "title": "Plate 4: a Corinthian capital on the ground to left in the foreground, a monument with figures in low relief to left in the middleground, various animals and two shepherds to right, a round composition, from 'Roman landscapes and ruins' (Paysages et ruines de Rome)",
        "country": "Italy",
        "culture": "",
        "image": "https://images.metmuseum.org/CRDImages/dp/original/DP828076.jpg"
    },
    {
        "title": "Plate 1: a monument with statues and a coat of arms in the center, a draughstman on the ground beneath a tree to right, two groups of lovers to left in the background, from 'Various landscapes' (Divers paysages)",
        "country": "Italy",
        "culture": "",
        "image": "https://images.metmuseum.org/CRDImages/dp/original/DP817810.jpg"
    },
    {
        "title": "Design for a Funerary Monument",
        "country": "France",
        "culture": "",
        "image": "https://images.metmuseum.org/CRDImages/dp/original/DP812623.jpg"
    },
    {
        "title": "Elevation of a Monument",
        "country": "France",
        "culture": "",
        "image": "https://images.metmuseum.org/CRDImages/dp/original/DP339580.jpg"
    },
    {
        "title": "Plate 1: fragments from ancient monuments, from 'Roman Landscapes and Ruins' (Paysages et ruines de Rome)",
        "country": "Italy",
        "culture": "",
        "image": "https://images.metmuseum.org/CRDImages/dp/original/DP817977.jpg"
    },
    {
        "title": "Design for a Funerary Monument",
        "country": "Germany",
        "culture": "",
        "image": "https://images.metmuseum.org/CRDImages/dp/original/DP809386.jpg"
    },
    {
        "title": "[Travelers By Ancient Monument]",
        "country": "",
        "culture": "",
        "image": "https://images.metmuseum.org/CRDImages/ph/original/DP71183.jpg"
    },
    {
        "title": "[Colonel Lawrence Monument, Lucknow, India]",
        "country": "",
        "culture": "",
        "image": "https://images.metmuseum.org/CRDImages/ph/original/DP71334.jpg"
    },
    {
        "title": "[Islamic Monument]",
        "country": "",
        "culture": "",
        "image": "https://images.metmuseum.org/CRDImages/ph/original/DP147386.jpg"
    },
    {
        "title": "Monuments of Paris",
        "country": "France",
        "culture": "",
        "image": "https://images.metmuseum.org/CRDImages/dp/original/DP820631.jpg"
    },
    {
        "title": "Antique Monuments",
        "country": "France",
        "culture": "",
        "image": "https://images.metmuseum.org/CRDImages/dp/original/53.523.69(2).jpg"
    },
    {
        "title": "[Ochterlony Monument, Calcutta]",
        "country": "Britain",
        "culture": "",
        "image": "https://images.metmuseum.org/CRDImages/ph/original/DP147436.jpg"
    },
    {
        "title": "Lord Hardinge's Monument, Calcutta",
        "country": "Britain",
        "culture": "",
        "image": "https://images.metmuseum.org/CRDImages/ph/original/DP147426.jpg"
    },
    {
        "title": "A man standing in front of three monuments",
        "country": "",
        "culture": "",
        "image": "https://images.metmuseum.org/CRDImages/dp/original/DP869251-1.jpg"
    },
    {
        "title": "Monuments of Paris",
        "country": "France",
        "culture": "",
        "image": "https://images.metmuseum.org/CRDImages/es/original/DP16375.jpg"
    },
    {
        "title": "Map of Ancient Rome Illustrating Major Monuments and the Seven Hills",
        "country": "Netherlands",
        "culture": "",
        "image": "https://images.metmuseum.org/CRDImages/dp/original/DP800332.jpg"
    },
    {
        "title": "Architectural Fantasy: Temple-like Building with Colonnades, a Monumental Staircase, and a Burnt Offering (Sacrifice) in the Foreground",
        "country": "Italy",
        "culture": "",
        "image": "https://images.metmuseum.org/CRDImages/dp/original/DP803658.jpg"
    },
    {
        "title": "Design for a Stage Set: Design in Section of a Two-Storied Entrance Hall (Recto). Elevation Design for a Monumental Entrance with Columns and Rounded Pediment (Verso).",
        "country": "Italy",
        "culture": "",
        "image": "https://images.metmuseum.org/CRDImages/dp/original/DP801341.jpg"
    },
    {
        "title": "[Group of 8 Early Stereograph Views of British Monuments, Memorials, and Tombs]",
        "country": "Britain, Scottish",
        "culture": "",
        "image": "https://images.metmuseum.org/CRDImages/ph/original/DP73049.jpg"
    },
    {
        "title": "Excursions Daguerriennes. Vues et monuments les plus remarquables du globe",
        "country": "France",
        "culture": "",
        "image": "https://images.metmuseum.org/CRDImages/ph/original/DP-15365-002.jpg"
    },
    {
        "title": "Printed Text Desribing the Monument of Eudo de Arsie (from The Topographer, no. XII, 1790)",
        "country": "",
        "culture": "",
        "image": "https://images.metmuseum.org/CRDImages/dp/original/DP829105.jpg"
    },
    {
        "title": "Design for a Festival Monument: Base Holds a Small Orchestra; Triumphal Arch Surmounted by a Cartouche-Decorated Pyramid with Figure of Fame, below, a Royal Crown.",
        "country": "Italy",
        "culture": "",
        "image": "https://images.metmuseum.org/CRDImages/dp/original/DP820198.jpg"
    },
    {
        "title": "Venetian Capriccio: Landscape with a Farm Building, Sarcophagus, and Fountain (recto);  Monument (verso)",
        "country": "Italy",
        "culture": "",
        "image": "https://images.metmuseum.org/CRDImages/dp/original/DP807982.jpg"
    },
    {
        "title": "Design for a Monumental Altar, Plate e from 'Unterschiedliche Neu Inventierte Altäre mit darzu gehörigen Profillen u. Grundrißen.'",
        "country": "",
        "culture": "",
        "image": "https://images.metmuseum.org/CRDImages/dp/original/DP703671.jpg"
    },
    {
        "title": "Design for a Monument to the Three Wives of the First Earl of Guilford, at Wroxton, Oxfordshire",
        "country": "Britain",
        "culture": "",
        "image": "https://images.metmuseum.org/CRDImages/dp/original/DP805243.jpg"
    },
    {
        "title": "Design for a Pedestal (recto); Design for the Plan of a Monument (verso)",
        "country": "Italy",
        "culture": "",
        "image": "https://images.metmuseum.org/CRDImages/dp/original/DP809629.jpg"
    },
    {
        "title": "Temple de Venus et de Rome, from Les Plus Beaux Monuments de Rome Ancienne ou Recueil des plus beaux Morceaux de l'Antiquité Romaine qui existent encore",
        "country": "France",
        "culture": "",
        "image": "https://images.metmuseum.org/CRDImages/dp/original/DP341370.jpg"
    },
    {
        "title": "Design for a sepulchral monument with a portrait bust; verso: Design for a reliquary (?)",
        "country": "Belgium",
        "culture": "",
        "image": "https://images.metmuseum.org/CRDImages/dp/original/DP808632.jpg"
    },
    {
        "title": "Design for a sepulchral monument with Mary Magdalen and Saint Jerome; verso: Sketch (counterproof) and writing exercises",
        "country": "Belgium",
        "culture": "",
        "image": "https://images.metmuseum.org/CRDImages/dp/original/DP808653.jpg"
    },
    {
        "title": "Design studies for monuments",
        "country": "Germany",
        "culture": "",
        "image": "https://images.metmuseum.org/CRDImages/dp/original/DP810460.jpg"
    },
    {
        "title": "Design for a sepulchral monument with a seated prophet or philosopher; verso: Sketches",
        "country": "Belgium",
        "culture": "",
        "image": "https://images.metmuseum.org/CRDImages/dp/original/DP808641.jpg"
    },
    {
        "title": "Design for a sepulchral monument with an allegory of Time; verso: Design for a column",
        "country": "Belgium",
        "culture": "",
        "image": "https://images.metmuseum.org/CRDImages/dp/original/DP808639.jpg"
    },
    {
        "title": "Architectural Capriccio with Roman Monuments and Washerwomen",
        "country": "France",
        "culture": "",
        "image": "https://images.metmuseum.org/CRDImages/dp/original/DP808080.jpg"
    },
    {
        "title": "Fanciful Landscape (Landscape with Villa Building and Equestrian Monument)",
        "country": "Italy",
        "culture": "",
        "image": "https://images.metmuseum.org/CRDImages/dp/original/DP801289.jpg"
    },
    {
        "title": "Design for a sepulchral monument in the form of a pulpit; verso: Fragment of a text",
        "country": "Belgium",
        "culture": "",
        "image": "https://images.metmuseum.org/CRDImages/dp/original/DP808655.jpg"
    },
    {
        "title": "Design for an Octagonal Table and Top (Recto); Design for altar or tomb monument (Verso)",
        "country": "Italy",
        "culture": "",
        "image": "https://images.metmuseum.org/CRDImages/dp/original/DP802151.jpg"
    },
    {
        "title": "Design for a Monumental Fountain",
        "country": "France",
        "culture": "",
        "image": "https://images.metmuseum.org/CRDImages/dp/original/DP811618.jpg"
    },
    {
        "title": "[View in Court of Christian Monuments; Views of Greece and Roman Sculpture Court]",
        "country": "Britain",
        "culture": "",
        "image": "https://images.metmuseum.org/CRDImages/ph/original/DP323105.jpg"
    },
    {
        "title": "[Court of Ancient Monuments; Germany Medieval Court; View with Statue of Albert of Bavaria; Elevated View of Central Transept]",
        "country": "Britain",
        "culture": "",
        "image": "https://images.metmuseum.org/CRDImages/ph/original/DP323126.jpg"
    },
    {
        "title": "A Vase and Classical Monuments Carved with Hooded Women Carrying Urns, Two Females Embracing Beneath a Vase and Two Nude Female Figures Supporting a Vase",
        "country": "Britain",
        "culture": "",
        "image": "https://images.metmuseum.org/CRDImages/dp/original/DP804430.jpg"
    },
    {
        "title": "Ornamental Design for a Wall Monument Surmounted by a Balustrade with Human Figures, Angels Holding Garlands and Draperies (recto and verso).",
        "country": "Italy",
        "culture": "",
        "image": "https://images.metmuseum.org/CRDImages/dp/original/DP809469.jpg"
    },
    {
        "title": "A Sheet of Studies with Architectural Motifs and Two Sketches for a Visitation (Recto). Sketch for a Funerary Monument (Verso)",
        "country": "Italy",
        "culture": "",
        "image": "https://images.metmuseum.org/CRDImages/dp/original/DP809549.jpg"
    },
    {
        "title": "XIVe Station. Le corps de Jésus est deposé dans le tombeau. Monument du St Sépulcre où le corps du Christ a été enseveli.",
        "country": "France",
        "culture": "",
        "image": "https://images.metmuseum.org/CRDImages/ph/original/DP345547.jpg"
    },
    {
        "title": "Design for a sepulchral monument with an allegory of Time; verso: Architectural sketch and fragment of a letter",
        "country": "Belgium",
        "culture": "",
        "image": "https://images.metmuseum.org/CRDImages/dp/original/DP808643.jpg"
    },
    {
        "title": "View of the Capitoline Hill during Michelangelo's restoration, the equestrian monument of Marcus Aurelius in the centre from the 'Speculum Romanae Magnificentiae:'",
        "country": "",
        "culture": "",
        "image": "https://images.metmuseum.org/CRDImages/dp/original/DP844273.jpg"
    },
    {
        "title": "Design for a sepulchral monument with a seated female figure; verso: Design for a statue of a standing male figure and fragment of a letter",
        "country": "Belgium",
        "culture": "",
        "image": "https://images.metmuseum.org/CRDImages/dp/original/DP808651.jpg"
    },
    {
        "title": "Leaf from Aedes Walpolinae mounted with a hand-written sheet, two prints and a printed sheet with drawn additions: (a): Sermon on Painting, continued; (b): St. Peter's Church at Walpole; (c): Chateau de Picton; (d): Monument of Eudo de Arsie; (e) Printed text describing Monument of Eudo de Arsie",
        "country": "Britain",
        "culture": "",
        "image": "https://images.metmuseum.org/CRDImages/dp/original/DP829095.jpg"
    },
    {
        "title": "Monumental vase",
        "country": "France",
        "culture": "",
        "image": "https://images.metmuseum.org/CRDImages/es/original/DP110448.jpg"
    },
    {
        "title": "Antiquities of Mexico : comprising fac-similes of ancient Mexican paintings and hieroglyphics, preserved in the Royal Libraries of Paris, Berlin, and Dresden ; in the Imperial Library of Vienna; in the Vatican Library ; in the Borgian Museum at Rome ; in the Library of the Institute at Bologna ; and in the Bodleian Library at Oxford.  Together with the Monuments of New Spain, by M. Dupaix: with their respective scales of measurement and accompanying descriptions. The whole illustrated by many valuable inedited manuscripts",
        "country": "Mexico",
        "culture": "",
        "image": "https://images.metmuseum.org/CRDImages/li/original/b1346521_05_001.jpg"
    },
    {
        "title": "Monumental mirror sconce (one of a pair)",
        "country": "",
        "culture": "",
        "image": "https://images.metmuseum.org/CRDImages/es/original/DP-15704-019.jpg"
    },
    {
        "title": "Monumental mirror sconce (one of a pair)",
        "country": "",
        "culture": "",
        "image": "https://images.metmuseum.org/CRDImages/es/original/DP-15704-018.jpg"
    },
    {
        "title": "Monument of Bishop Mays, Hereford Castle AD1516",
        "country": "Britain",
        "culture": "",
        "image": "https://images.metmuseum.org/CRDImages/dp/original/DP805324.jpg"
    },
    {
        "title": "[Two Men by Monumental Elephant Statues, China]",
        "country": "China",
        "culture": "",
        "image": "https://images.metmuseum.org/CRDImages/ph/original/DP71225.jpg"
    },
    {
        "title": "Monuments and Chancel Steps, Tenby Church",
        "country": "Britain",
        "culture": "",
        "image": "https://images.metmuseum.org/CRDImages/ph/original/DP112674.jpg"
    },
    {
        "title": "Project for a Monumental Fountain",
        "country": "France",
        "culture": "",
        "image": "https://images.metmuseum.org/CRDImages/dp/original/DP-293-001.jpg"
    },
    {
        "title": "Project for a Monumental Tomb",
        "country": "Italy",
        "culture": "",
        "image": "https://images.metmuseum.org/CRDImages/dp/original/DP801956.jpg"
    },
    {
        "title": "Monumental Figure",
        "country": "",
        "culture": "Maya",
        "image": "https://images.metmuseum.org/CRDImages/ao/original/DT5130.jpg"
    },
    {
        "title": "Ancient Naval Battle (Recto); Park with Monuments (Verso)",
        "country": "Italy",
        "culture": "",
        "image": "https://images.metmuseum.org/CRDImages/dp/original/DP802161.jpg"
    },
    {
        "title": "Les Monuments Romains",
        "country": "France",
        "culture": "",
        "image": "https://images.metmuseum.org/CRDImages/dp/original/DP819865.jpg"
    },
    {
        "title": "Design for coffered cupola interior and monuments (recto); details of wall decoration (verso)",
        "country": "",
        "culture": "",
        "image": "https://images.metmuseum.org/CRDImages/dp/original/DP804518.jpg"
    },
    {
        "title": "Design for a Stage Set with a Monumental Arcaded Courtyard.",
        "country": "Italy",
        "culture": "",
        "image": "https://images.metmuseum.org/CRDImages/dp/original/DP801284.jpg"
    },
    {
        "title": "A Monumental Archway with Five Bays in the Corinthian Order",
        "country": "France",
        "culture": "",
        "image": "https://images.metmuseum.org/CRDImages/dp/original/DP211509.jpg"
    },
    {
        "title": "Design for an Altar or Monument with Angels and Other Figures",
        "country": "",
        "culture": "",
        "image": "https://images.metmuseum.org/CRDImages/dp/original/DP803548.jpg"
    },
    {
        "title": "[View of the City from the Ochterlony Monument, Calcutta]",
        "country": "Britain",
        "culture": "",
        "image": "https://images.metmuseum.org/CRDImages/ph/original/DP147437.jpg"
    },
    {
        "title": "Excursions Daguerriennes. Vues et monuments les plus remarquables du globe",
        "country": "France",
        "culture": "",
        "image": "https://images.metmuseum.org/CRDImages/ph/original/DP-15366-001.jpg"
    },
    {
        "title": "Monumental Bodhisattva Head",
        "country": "Pakistan",
        "culture": "Pakistan (ancient region of Gandhara)",
        "image": "https://images.metmuseum.org/CRDImages/as/original/DP123384.jpg"
    },
    {
        "title": "Obelisk Grave Monument, No. 16",
        "country": "",
        "culture": "",
        "image": "https://images.metmuseum.org/CRDImages/dp/original/DP885519.jpg"
    },
    {
        "title": "Obelisk Grave Monument, No. 84",
        "country": "",
        "culture": "",
        "image": "https://images.metmuseum.org/CRDImages/dp/original/DP885521.jpg"
    },
    {
        "title": "Obelisk Grave Monument, No. 34",
        "country": "",
        "culture": "",
        "image": "https://images.metmuseum.org/CRDImages/dp/original/DP885520.jpg"
    },
    {
        "title": "A uniface medal of the Ancient Greek and Egyptian Monuments of the Louvre",
        "country": "",
        "culture": "",
        "image": "https://images.metmuseum.org/CRDImages/es/original/DP100565.jpg"
    },
    {
        "title": "Design for a Proscenium or Monumental Alcove",
        "country": "Italy",
        "culture": "",
        "image": "https://images.metmuseum.org/CRDImages/dp/original/DP809625.jpg"
    },
    {
        "title": "The Monumental Tablet, from Grotteschi (Grotesques)",
        "country": "Italy",
        "culture": "",
        "image": "https://images.metmuseum.org/CRDImages/dp/original/DP828188.jpg"
    },
    {
        "title": "Vases; Set of Wall Monuments; Statue of Louis XV",
        "country": "France",
        "culture": "",
        "image": "https://images.metmuseum.org/CRDImages/dp/original/DP830531.jpg"
    },
    {
        "title": "Design for a Monumental Altar, Plate a from 'Unterschiedliche Neu Inventierte Altäre mit darzu gehörigen Profillen u. Grundrißen.'",
        "country": "",
        "culture": "",
        "image": "https://images.metmuseum.org/CRDImages/dp/original/DP703663.jpg"
    },
    {
        "title": "The Beginning of Autumn (Monument Mountain near Stockbridge)(from McGuire Scrapbook)",
        "country": "American",
        "culture": "American",
        "image": "https://images.metmuseum.org/CRDImages/ad/original/65079.jpg"
    },
    {
        "title": "Visitant l'intérieur des principaux monuments de Paris, from Actualités, published in Le Charivari, March 9, 1859",
        "country": "",
        "culture": "",
        "image": "https://images.metmuseum.org/CRDImages/dp/original/DP876841.jpg"
    },
    {
        "title": "Jerusalem, Etude et reproduction photographique des monuments de la ville sainte depuis l' époque judaique jusqu'à nos jours 1856",
        "country": "France",
        "culture": "",
        "image": "https://images.metmuseum.org/CRDImages/ph/original/DP131395.jpg"
    },
    {
        "title": "Design for a Wall Tomb or Monument (Recto); Smaller Variant Version with Half Length Madonna & Child on Crescent Moon (Verso)",
        "country": "Italy",
        "culture": "",
        "image": "https://images.metmuseum.org/CRDImages/dp/original/DP811050.jpg"
    },
    {
        "title": "Architectural Design for a Monumental Altar, with a Composition with Saint Michael Against Satan and two Saints (Saints Peter and Paul?)",
        "country": "",
        "culture": "",
        "image": "https://images.metmuseum.org/CRDImages/dp/original/DP820253.jpg"
    },
    {
        "title": "Design for the Corner of a Decoration (recto); Sketch of Monumental Building with Four Temple-Front Entrances (verso)",
        "country": "France",
        "culture": "",
        "image": "https://images.metmuseum.org/CRDImages/dp/original/DP807106.jpg"
    },
    {
        "title": "Monumental vase",
        "country": "France",
        "culture": "",
        "image": "https://images.metmuseum.org/CRDImages/es/original/DP704028.jpg"
    },
    {
        "title": "Design for a sepulchral monument; verso: Fragment of a letter and notes",
        "country": "Belgium",
        "culture": "",
        "image": "https://images.metmuseum.org/CRDImages/dp/original/DP808647.jpg"
    },
    {
        "title": "Design for a monument; verso: Architectural sketches",
        "country": "Belgium",
        "culture": "",
        "image": "https://images.metmuseum.org/CRDImages/dp/original/DP808648.jpg"
    },
    {
        "title": "Plate 1: various fragments of ancient monuments, a round composition, from 'Roman landscapes and ruins' (Paysages et ruines de Rome)",
        "country": "Italy",
        "culture": "",
        "image": "https://images.metmuseum.org/CRDImages/dp/original/DP828071.jpg"
    },
    {
        "title": "Obelisk Grave Monument, No. 901 / 920",
        "country": "",
        "culture": "",
        "image": "https://images.metmuseum.org/CRDImages/dp/original/DP885522.jpg"
    },
    {
        "title": "Design for a Monumental Altar, Plate 'p' from 'Unterschiedliche Neu Inventierte Altäre mit darzu gehörigen Profillen u. Grundrißen.'",
        "country": "",
        "culture": "",
        "image": "https://images.metmuseum.org/CRDImages/dp/original/DP703685.jpg"
    },
    {
        "title": "Manuscript page with a Project for a Fountain (recto) and Project and Plan for a Monumental Staircase (verso)",
        "country": "Italy",
        "culture": "",
        "image": "https://images.metmuseum.org/CRDImages/dp/original/DP801676.jpg"
    },
    {
        "title": "Design for a Monumental Altar, Plate b from 'Unterschiedliche Neu Inventierte Altäre mit darzu gehörigen Profillen u. Grundrißen.'",
        "country": "",
        "culture": "",
        "image": "https://images.metmuseum.org/CRDImages/dp/original/DP703665.jpg"
    },
    {
        "title": "Prometheus chained, two pendentives and an egyptian Saint Marie, bound in Monuments des Arts du Dessin, volume 3, plate 234",
        "country": "",
        "culture": "",
        "image": "https://images.metmuseum.org/CRDImages/dp/original/DP836601.jpg"
    },
    {
        "title": "Design for a Monumental Altar, Plate h from 'Unterschiedliche Neu Inventierte Altäre mit darzu gehörigen Profillen u. Grundrißen.'",
        "country": "",
        "culture": "",
        "image": "https://images.metmuseum.org/CRDImages/dp/original/DP703678.jpg"
    },
    {
        "title": "Design for a Monumental Altar, Plate n from 'Unterschiedliche Neu Inventierte Altäre mit darzu gehörigen Profillen u. Grundrißen.'",
        "country": "",
        "culture": "",
        "image": "https://images.metmuseum.org/CRDImages/dp/original/DP703683.jpg"
    },
    {
        "title": "Design for a Monumental Altar, Plate f from 'Unterschiedliche Neu Inventierte Altäre mit darzu gehörigen Profillen u. Grundrißen.'",
        "country": "",
        "culture": "",
        "image": "https://images.metmuseum.org/CRDImages/dp/original/DP703673.jpg"
    },
    {
        "title": "Design for a Monumental Altar, Plate g from 'Unterschiedliche Neu Inventierte Altäre mit darzu gehörigen Profillen u. Grundrißen.'",
        "country": "",
        "culture": "",
        "image": "https://images.metmuseum.org/CRDImages/dp/original/DP703675.jpg"
    },
    {
        "title": "Architectural Capriccio with a Monumental Arch",
        "country": "Italy",
        "culture": "",
        "image": "https://images.metmuseum.org/CRDImages/dp/original/DP167485.jpg"
    },
    {
        "title": "Jerusalem, Etude et reproduction photographique des monuments de la ville sainte depuis l' époque judaique jusqu'à nos jours 1856",
        "country": "France",
        "culture": "",
        "image": "https://images.metmuseum.org/CRDImages/ph/original/DP131395.jpg"
    },
    {
        "title": "Égypte, Nubie, Syrie: Paysages et Monuments",
        "country": "France",
        "culture": "",
        "image": "https://images.metmuseum.org/CRDImages/ph/original/DP131988.jpg"
    },
    {
        "title": "Design for a Monumental Altar, Plate 'q' from 'Unterschiedliche Neu Inventierte Altäre mit darzu gehörigen Profillen u. Grundrißen.'",
        "country": "",
        "culture": "",
        "image": "https://images.metmuseum.org/CRDImages/dp/original/DP703686.jpg"
    },
    {
        "title": "Design for a Monumental Altar, Plate 'o' (?)  from 'Unterschiedliche Neu Inventierte Altäre mit darzu gehörigen Profillen u. Grundrißen.'",
        "country": "",
        "culture": "",
        "image": "https://images.metmuseum.org/CRDImages/dp/original/DP703684.jpg"
    },
    {
        "title": "Plate 19: Part of the ancient Appian Way about three miles outside Porta S. Sebastiano, from Alcune Vedute di Archi Trionfali ed altri monumenti inalzati da Romani parte de quali se veggono in Roma e parte per l'Italia (Some Views of Triumphal Arches and other monuments erected by the Romans, some of which are in Rome and some elsewhere in Italy)",
        "country": "Italy",
        "culture": "",
        "image": "https://images.metmuseum.org/CRDImages/dp/original/DP827964.jpg"
    },
    {
        "title": "Title page: volume IV, 'The Antiquities of Rome by Giambatista Piranesi, Venetian Architect. Volume 4, containing the ancient bridges, the remains of theaters, of porticoes, and of other monuments of Rome' (Le antichità romane di Giambatista Piranesi architetto veneziano. Tomo quarto, contenente i ponti antichi, gli avanzi de' teatri, de' portici, e di altri monumenti di Roma), from the series 'Roman Antiquities' (Le Antichità Romane)",
        "country": "Italy",
        "culture": "",
        "image": "https://images.metmuseum.org/CRDImages/dp/original/DP831904.jpg"
    },
    {
        "title": "Design for a Monumental Altar, Plate L from 'Unterschiedliche Neu Inventierte Altäre mit darzu gehörigen Profillen u. Grundrißen.'",
        "country": "",
        "culture": "",
        "image": "https://images.metmuseum.org/CRDImages/dp/original/DP703681.jpg"
    },
    {
        "title": "Design for a Monumental Altar, Plate m from 'Unterschiedliche Neu Inventierte Altäre mit darzu gehörigen Profillen u. Grundrißen.'",
        "country": "",
        "culture": "",
        "image": "https://images.metmuseum.org/CRDImages/dp/original/DP703682.jpg"
    },
    {
        "title": "Design for a Monumental Altar, Plate d from 'Unterschiedliche Neu Inventierte Altäre mit darzu gehörigen Profillen u. Grundrißen.'",
        "country": "",
        "culture": "",
        "image": "https://images.metmuseum.org/CRDImages/dp/original/DP703669.jpg"
    },
    {
        "title": "Design for a Monumental Altar, Plate i from 'Unterschiedliche Neu Inventierte Altäre mit darzu gehörigen Profillen u. Grundrißen.'",
        "country": "",
        "culture": "",
        "image": "https://images.metmuseum.org/CRDImages/dp/original/DP703679.jpg"
    },
    {
        "title": "Design for a Monumental Altar, Plate c from 'Unterschiedliche Neu Inventierte Altäre mit darzu gehörigen Profillen u. Grundrißen.'",
        "country": "",
        "culture": "",
        "image": "https://images.metmuseum.org/CRDImages/dp/original/DP703667.jpg"
    },
    {
        "title": "Les monuments d'Égypte",
        "country": "France",
        "culture": "",
        "image": "https://images.metmuseum.org/CRDImages/es/original/DP109796.jpg"
    },
    {
        "title": "Design for a Monumental Altar, Plate k from 'Unterschiedliche Neu Inventierte Altäre mit darzu gehörigen Profillen u. Grundrißen.'",
        "country": "",
        "culture": "",
        "image": "https://images.metmuseum.org/CRDImages/dp/original/DP703680.jpg"
    },
    {
        "title": "[Tomb of Lorenzo de Medici; Tomb of Giuliano de Medici; Court of Christian Monuments; Germany Medieval Vestibule]",
        "country": "Britain",
        "culture": "",
        "image": "https://images.metmuseum.org/CRDImages/ph/original/DP323132.jpg"
    },
    {
        "title": "[Medieval Court; Statue of Coleoni; Equestrian Statue of Gattamelata by Donatello, from the Court of Monuments of Christian Art; Equestrian Statue of Colleone]",
        "country": "Britain",
        "culture": "",
        "image": "https://images.metmuseum.org/CRDImages/ph/original/DP323103.jpg"
    },
    {
        "title": "Sketches of a Funeral Monument, a Niche with Statues, a Helmet in the Shape of a Human Head, an Entablature and a Female Statue",
        "country": "Italy",
        "culture": "",
        "image": "https://images.metmuseum.org/CRDImages/dp/original/DP810673.jpg"
    },
    {
        "title": "Vue d'une partie du Palais des Cesars du côté de Campo Vaccino, batie par l'Empereur Caligula, from Les Plus Beaux Monuments de Rome Ancienne ou Recueil des plus beaux Morceaux de l'Antiquité Romaine qui existent encore",
        "country": "France",
        "culture": "",
        "image": "https://images.metmuseum.org/CRDImages/dp/original/DP341368.jpg"
    },
    {
        "title": "Stele of Ushumgal",
        "country": "",
        "culture": "Sumerian",
        "image": "https://images.metmuseum.org/CRDImages/an/original/DT849.jpg"
    },
    {
        "title": "Marble grave stele of a young woman and servant",
        "country": "",
        "culture": "Greece, Attic",
        "image": "https://images.metmuseum.org/CRDImages/gr/original/DT11989.jpg"
    },
    {
        "title": "Fragment of the marble stele (grave marker) of a hoplite (foot soldier)",
        "country": "",
        "culture": "Greece, Attic",
        "image": "https://images.metmuseum.org/CRDImages/gr/original/DT281370.jpg"
    },
    {
        "title": "Marble grave stele with a family group",
        "country": "",
        "culture": "Greece, Attic",
        "image": "https://images.metmuseum.org/CRDImages/gr/original/DT281.jpg"
    },
    {
        "title": "Stele of the protective goddess Lama",
        "country": "",
        "culture": "Kassite",
        "image": "https://images.metmuseum.org/CRDImages/an/original/DP-1556-001.jpg"
    },
    {
        "title": "Stele",
        "country": "",
        "culture": "",
        "image": "https://images.metmuseum.org/CRDImages/is/original/9173b.jpg"
    },
    {
        "title": "Marble grave stele of Antigenes",
        "country": "",
        "culture": "Greece, Attic",
        "image": "https://images.metmuseum.org/CRDImages/gr/original/DT231007.jpg"
    },
    {
        "title": "Stele",
        "country": "",
        "culture": "",
        "image": "https://images.metmuseum.org/CRDImages/is/original/9173a.jpg"
    },
    {
        "title": "Stele",
        "country": "",
        "culture": "",
        "image": "https://images.metmuseum.org/CRDImages/is/original/10.175.111.JPG"
    },
    {
        "title": "Stele",
        "country": "",
        "culture": "",
        "image": "https://images.metmuseum.org/CRDImages/is/original/9173.jpg"
    },
    {
        "title": "Stele",
        "country": "",
        "culture": "China",
        "image": "https://images.metmuseum.org/CRDImages/as/original/47_6_F2x.JPG"
    },
    {
        "title": "Stele",
        "country": "",
        "culture": "",
        "image": "https://images.metmuseum.org/CRDImages/is/original/10.176.24.JPG"
    },
    {
        "title": "Stele",
        "country": "",
        "culture": "China",
        "image": "https://images.metmuseum.org/CRDImages/as/original/14_94_24064.JPG"
    },
    {
        "title": "Stele",
        "country": "",
        "culture": "",
        "image": "https://images.metmuseum.org/CRDImages/is/original/10.175.6.JPG"
    },
    {
        "title": "Stele",
        "country": "",
        "culture": "",
        "image": "https://images.metmuseum.org/CRDImages/is/original/10.176.6.jpg"
    },
    {
        "title": "Marble grave stele of a little girl",
        "country": "",
        "culture": "Greece",
        "image": "https://images.metmuseum.org/CRDImages/gr/original/DT279.jpg"
    },
    {
        "title": "Stele",
        "country": "",
        "culture": "",
        "image": "https://images.metmuseum.org/CRDImages/is/original/10.175.103.JPG"
    },
    {
        "title": "Stele",
        "country": "",
        "culture": "",
        "image": "https://images.metmuseum.org/CRDImages/is/original/10.175.109.JPG"
    },
    {
        "title": "Stele",
        "country": "",
        "culture": "",
        "image": "https://images.metmuseum.org/CRDImages/is/original/10.175.113.JPG"
    },
    {
        "title": "Stele",
        "country": "",
        "culture": "",
        "image": "https://images.metmuseum.org/CRDImages/is/original/10.175.60.JPG"
    },
    {
        "title": "Stele",
        "country": "",
        "culture": "",
        "image": "https://images.metmuseum.org/CRDImages/is/original/10.175.107.JPG"
    },
    {
        "title": "Stele",
        "country": "",
        "culture": "",
        "image": "https://images.metmuseum.org/CRDImages/is/original/10.175.42.JPG"
    },
    {
        "title": "Stele",
        "country": "",
        "culture": "",
        "image": "https://images.metmuseum.org/CRDImages/is/original/08.205.10d.JPG"
    },
    {
        "title": "Stele",
        "country": "",
        "culture": "",
        "image": "https://images.metmuseum.org/CRDImages/is/original/10.175.110.JPG"
    },
    {
        "title": "Stele",
        "country": "",
        "culture": "",
        "image": "https://images.metmuseum.org/CRDImages/is/original/10.175.44.JPG"
    },
    {
        "title": "Stele",
        "country": "",
        "culture": "",
        "image": "https://images.metmuseum.org/CRDImages/is/original/10.175.74.JPG"
    },
    {
        "title": "Stele",
        "country": "",
        "culture": "",
        "image": "https://images.metmuseum.org/CRDImages/is/original/LC_10_175_17s01.jpg"
    },
    {
        "title": "Stele",
        "country": "",
        "culture": "",
        "image": "https://images.metmuseum.org/CRDImages/is/original/10.175.69.JPG"
    },
    {
        "title": "Stele",
        "country": "",
        "culture": "",
        "image": "https://images.metmuseum.org/CRDImages/is/original/20.8.1.jpg"
    },
    {
        "title": "Stele",
        "country": "",
        "culture": "",
        "image": "https://images.metmuseum.org/CRDImages/is/original/LC_10_175_13s01.jpg"
    },
    {
        "title": "Marble stele (grave marker) of a young girl",
        "country": "",
        "culture": "Greece, Boeotian",
        "image": "https://images.metmuseum.org/CRDImages/gr/original/GR43.jpg"
    },
    {
        "title": "Limestone funerary stele (shaft) with a \"Cypriot capital\"",
        "country": "",
        "culture": "Cypriot",
        "image": "https://images.metmuseum.org/CRDImages/gr/original/DP263895.jpg"
    },
    {
        "title": "Funerary Stele with Wheel Pattern",
        "country": "",
        "culture": "",
        "image": "https://images.metmuseum.org/CRDImages/is/original/wb-10.176.25.JPG"
    },
    {
        "title": "Funerary Stele with Cross Medallion",
        "country": "",
        "culture": "",
        "image": "https://images.metmuseum.org/CRDImages/is/original/08.246.JPG"
    },
    {
        "title": "Marble stele (grave marker) of a woman",
        "country": "",
        "culture": "Greece, Attic",
        "image": "https://images.metmuseum.org/CRDImages/gr/original/DT11995.jpg"
    },
    {
        "title": "Eight Great Events Stele",
        "country": "",
        "culture": "Eastern India (Bihar)",
        "image": "https://images.metmuseum.org/CRDImages/as/original/DP-592-001.jpg"
    },
    {
        "title": "Funerary Stele with Cross at Center in Architectural Frame",
        "country": "",
        "culture": "",
        "image": "https://images.metmuseum.org/CRDImages/is/original/9070b.jpg"
    },
    {
        "title": "Funerary Stele with Ankh (Looped Cross) Featuring a Human Face at the Center",
        "country": "",
        "culture": "",
        "image": "https://images.metmuseum.org/CRDImages/is/original/10.176.29.jpg"
    },
    {
        "title": "Funerary Stele with Two Lions and Circle Pattern",
        "country": "",
        "culture": "",
        "image": "https://images.metmuseum.org/CRDImages/is/original/9262a.jpg"
    },
    {
        "title": "Funerary Stele with Architectural Frame",
        "country": "",
        "culture": "",
        "image": "https://images.metmuseum.org/CRDImages/is/original/DP368679.jpg"
    },
    {
        "title": "Funerary Stele with Orant Figure in Architectural Frame",
        "country": "",
        "culture": "",
        "image": "https://images.metmuseum.org/CRDImages/is/original/8757.jpg"
    },
    {
        "title": "Fragment from a Funerary Stele with a Medallion of a Cross and Leaves",
        "country": "",
        "culture": "",
        "image": "https://images.metmuseum.org/CRDImages/is/original/10.175.89.JPG"
    },
    {
        "title": "Fragmentary marble grave stele",
        "country": "",
        "culture": "Greece, Attic",
        "image": "https://images.metmuseum.org/CRDImages/gr/original/DT324257.jpg"
    },
    {
        "title": "Funerary Stele with Cross Medallion below Eagle at Center in Architectural Frame",
        "country": "",
        "culture": "",
        "image": "https://images.metmuseum.org/CRDImages/is/original/9070a.jpg"
    },
    {
        "title": "Stele of the Xuanmi Pagoda",
        "country": "",
        "culture": "China",
        "image": "https://images.metmuseum.org/CRDImages/as/original/DP-18070-020.jpg"
    },
    {
        "title": "Marble stele (grave marker) of Eukleia",
        "country": "",
        "culture": "Greece, Attic",
        "image": "https://images.metmuseum.org/CRDImages/gr/original/GR66.jpg"
    },
    {
        "title": "Funerary Stele with Chi-Rho and Alpha and Omega",
        "country": "",
        "culture": "",
        "image": "https://images.metmuseum.org/CRDImages/is/original/18.5.4.JPG"
    },
    {
        "title": "Marble stele with a Lydian inscription",
        "country": "",
        "culture": "Lydian",
        "image": "https://images.metmuseum.org/CRDImages/gr/original/DP330878.jpg"
    },
    {
        "title": "Funerary Stele with Eagle in Architectural Frame",
        "country": "",
        "culture": "",
        "image": "https://images.metmuseum.org/CRDImages/is/original/21177.jpg"
    },
    {
        "title": "Marble grave stele of a woman",
        "country": "",
        "culture": "Greece, Boeotian",
        "image": "https://images.metmuseum.org/CRDImages/gr/original/GR25.jpg"
    },
    {
        "title": "Grave stele with Hoplite Battle Scene",
        "country": "",
        "culture": "Greece, Attic",
        "image": "https://images.metmuseum.org/CRDImages/gr/original/DT259950.jpg"
    },
    {
        "title": "Stele Commissioned by Helian Ziyue (赫蓮子悅) and a Devotional Society of Five Hundred Individuals",
        "country": "",
        "culture": "China",
        "image": "https://images.metmuseum.org/CRDImages/as/original/DP228202.jpg"
    },
    {
        "title": "Marble grave stele of Demetrios",
        "country": "",
        "culture": "Greece, Cypriot",
        "image": "https://images.metmuseum.org/CRDImages/gr/original/DP138665.jpg"
    },
    {
        "title": "Marble stele (grave marker) of a youth and little girl with capital and finial in the form of a sphinx",
        "country": "",
        "culture": "Greece, Attic",
        "image": "https://images.metmuseum.org/CRDImages/gr/original/DP116926.jpg"
    },
    {
        "title": "Marble stele (grave marker) of Sostratos",
        "country": "",
        "culture": "Greece, Attic",
        "image": "https://images.metmuseum.org/CRDImages/gr/original/DT269112.jpg"
    },
    {
        "title": "Marble stele (grave marker) of Lysistrate",
        "country": "",
        "culture": "Greece, Attic",
        "image": "https://images.metmuseum.org/CRDImages/gr/original/GR40.jpg"
    },
    {
        "title": "Marble stele (grave marker) of Phainippe",
        "country": "",
        "culture": "Greece, Attic",
        "image": "https://images.metmuseum.org/CRDImages/gr/original/GR7.jpg"
    },
    {
        "title": "Limestone funerary stele with antithetical sphinxes",
        "country": "",
        "culture": "Cypriot",
        "image": "https://images.metmuseum.org/CRDImages/gr/original/DP141216.jpg"
    },
    {
        "title": "Marble stele (grave marker) of a youth and a little girl",
        "country": "",
        "culture": "Greece, Attic",
        "image": "https://images.metmuseum.org/CRDImages/gr/original/DP116926.jpg"
    },
    {
        "title": "Fragment of the marble stele (grave marker) of a youth",
        "country": "",
        "culture": "Greece, Attic",
        "image": "https://images.metmuseum.org/CRDImages/gr/original/DT324258.jpg"
    },
    {
        "title": "Stele with the Bodhisattvas Avalokiteshvara (Guanyin) and Mahasthamaprapta (Dashizi)",
        "country": "",
        "culture": "China (Henan province)",
        "image": "https://images.metmuseum.org/CRDImages/as/original/DP213352.jpg"
    },
    {
        "title": "Finial of a marble stele (grave marker)",
        "country": "",
        "culture": "Greece, Attic",
        "image": "https://images.metmuseum.org/CRDImages/gr/original/DP119148.jpg"
    },
    {
        "title": "Painted limestone funerary stele with a woman in childbirth",
        "country": "",
        "culture": "Greece",
        "image": "https://images.metmuseum.org/CRDImages/gr/original/DP330006.jpg"
    },
    {
        "title": "Stele Commissioned by Li Zhewang (李真王), Yao Langzi (姚郎字), and Other Members of a Devotional Society",
        "country": "",
        "culture": "China",
        "image": "https://images.metmuseum.org/CRDImages/as/original/DP170274.jpg"
    },
    {
        "title": "Part of the marble stele (grave marker) of Kalliades",
        "country": "",
        "culture": "Greece, Attic",
        "image": "https://images.metmuseum.org/CRDImages/gr/original/DT324254.jpg"
    },
    {
        "title": "Fragment of a marble stele (grave marker)",
        "country": "",
        "culture": "Greece, Attic",
        "image": "https://images.metmuseum.org/CRDImages/gr/original/GR24.jpg"
    },
    {
        "title": "Upper part of the marble stele (grave marker) of Kallidemos",
        "country": "",
        "culture": "Greece, Attic",
        "image": "https://images.metmuseum.org/CRDImages/gr/original/GR57.jpg"
    },
    {
        "title": "Finial of a marble stele (grave marker)",
        "country": "",
        "culture": "Greece, Attic",
        "image": "https://images.metmuseum.org/CRDImages/gr/original/DT324255.jpg"
    },
    {
        "title": "Marble stele (grave marker) of a man",
        "country": "",
        "culture": "Greece, Attic",
        "image": "https://images.metmuseum.org/CRDImages/gr/original/GR200.jpg"
    },
    {
        "title": "Head of a youth from a marble stele (grave marker)",
        "country": "",
        "culture": "Greece, Attic",
        "image": "https://images.metmuseum.org/CRDImages/gr/original/DP116928.jpg"
    },
    {
        "title": "Fragment of a marble grave stele of a woman",
        "country": "",
        "culture": "Greece, Attic",
        "image": "https://images.metmuseum.org/CRDImages/gr/original/DT247660.jpg"
    },
    {
        "title": "Marble stele (grave marker) of a woman",
        "country": "",
        "culture": "Greece, Attic",
        "image": "https://images.metmuseum.org/CRDImages/gr/original/DT323837.jpg"
    },
    {
        "title": "Limestone funerary stele (shaft) surmounted by two sphinxes",
        "country": "",
        "culture": "Cypriot",
        "image": "https://images.metmuseum.org/CRDImages/gr/original/DP263896.jpg"
    },
    {
        "title": "Stele with Eight Great Events from the Life of the Buddha",
        "country": "",
        "culture": "India, Bihar, possibly from Nalanda",
        "image": "https://images.metmuseum.org/CRDImages/as/original/11r1_61B.jpg"
    },
    {
        "title": "Marble head of a man from a grave stele",
        "country": "",
        "culture": "Greece, Attic",
        "image": "https://images.metmuseum.org/CRDImages/gr/original/GR51.jpg"
    },
    {
        "title": "Limestone pediment from a funerary stele (shaft)",
        "country": "",
        "culture": "Cypriot",
        "image": "https://images.metmuseum.org/CRDImages/gr/original/DP263865.jpg"
    },
    {
        "title": "Painted limestone funerary stele with a seated man and two standing figures",
        "country": "",
        "culture": "Greece",
        "image": "https://images.metmuseum.org/CRDImages/gr/original/DP138732.jpg"
    },
    {
        "title": "Limestone stele (shaft) with the head of Hathor",
        "country": "",
        "culture": "Cypriot",
        "image": "https://images.metmuseum.org/CRDImages/gr/original/DP263876.jpg"
    },
    {
        "title": "Fragments of the marble stele (grave marker) of a woman holding a baby",
        "country": "",
        "culture": "Greece, Attic",
        "image": "https://images.metmuseum.org/CRDImages/gr/original/154405.jpg"
    },
    {
        "title": "Buddha (Fragment from a Larger Stele)",
        "country": "",
        "culture": "China",
        "image": "https://images.metmuseum.org/CRDImages/as/original/DP170196.jpg"
    },
    {
        "title": "Marble fragment of a stele (grave marker) of a youth",
        "country": "Greece",
        "culture": "Greece",
        "image": "https://images.metmuseum.org/CRDImages/gr/original/DP261226.jpg"
    },
    {
        "title": "Marble head of a girl probably from a stele (grave marker)",
        "country": "Greece",
        "culture": "Greece",
        "image": "https://images.metmuseum.org/CRDImages/gr/original/111649.jpg"
    },
    {
        "title": "Fragments of the marble stele (grave marker) of a woman holding a baby",
        "country": "Greece",
        "culture": "Greece, Attic",
        "image": "https://images.metmuseum.org/CRDImages/gr/original/154405.jpg"
    },
    {
        "title": "Marble head of a bearded man from a stele (grave marker)",
        "country": "Greece",
        "culture": "Greece, Attic",
        "image": "https://images.metmuseum.org/CRDImages/gr/original/199628.jpg"
    },
    {
        "title": "Fragment of a marble grave stele with the head of a youth",
        "country": "",
        "culture": "Greece",
        "image": "https://images.metmuseum.org/CRDImages/gr/original/DP330876.jpg"
    },
    {
        "title": "Fragmentary marble grave stele of a hoplite (foot soldier)",
        "country": "",
        "culture": "Greece, Attic",
        "image": "https://images.metmuseum.org/CRDImages/gr/original/GR49.jpg"
    },
    {
        "title": "Stele for Shi Chen",
        "country": "",
        "culture": "China",
        "image": "https://images.metmuseum.org/CRDImages/as/original/1992_166_2ab.jpg"
    },
    {
        "title": "Yan Family Temple Stele",
        "country": "China",
        "culture": "China",
        "image": "https://images.metmuseum.org/CRDImages/as/original/1977_375_14a_d_sf.JPG"
    },
    {
        "title": "Miniature Stele",
        "country": "",
        "culture": "China",
        "image": "https://images.metmuseum.org/CRDImages/as/original/30_76_126_O1.jpg"
    },
    {
        "title": "Miniature Stele",
        "country": "",
        "culture": "China",
        "image": "https://images.metmuseum.org/CRDImages/as/original/30_76_137_O1.jpg"
    },
    {
        "title": "Fragment of a Stele",
        "country": "",
        "culture": "",
        "image": "https://images.metmuseum.org/CRDImages/is/original/10.175.63.JPG"
    },
    {
        "title": "Fragment of a Stele",
        "country": "",
        "culture": "",
        "image": "https://images.metmuseum.org/CRDImages/is/original/10.175.32.JPG"
    },
    {
        "title": "Fragments of a Stele",
        "country": "",
        "culture": "",
        "image": "https://images.metmuseum.org/CRDImages/is/original/118073.jpg"
    },
    {
        "title": "Stele of Apa Moses",
        "country": "",
        "culture": "",
        "image": "https://images.metmuseum.org/CRDImages/is/original/08.205.10a.JPG"
    },
    {
        "title": "Stele of \"Blessed Chrysaphios\"",
        "country": "",
        "culture": "",
        "image": "https://images.metmuseum.org/CRDImages/is/original/LC_10_175_14s01.jpg"
    },
    {
        "title": "Stele of 'Sister Helen of Hage'",
        "country": "",
        "culture": "",
        "image": "https://images.metmuseum.org/CRDImages/is/original/08.205.10c.JPG"
    },
    {
        "title": "Stele fragment",
        "country": "Syria",
        "culture": "Syria",
        "image": "https://images.metmuseum.org/CRDImages/an/original/MEX196.jpg"
    },
    {
        "title": "Stele with Buddha Maitreya",
        "country": "China",
        "culture": "China",
        "image": "https://images.metmuseum.org/CRDImages/as/original/DP222959.jpg"
    },
    {
        "title": "Fragment of Stele",
        "country": "",
        "culture": "",
        "image": "https://images.metmuseum.org/CRDImages/is/original/sf18-5-5a.jpg"
    },
    {
        "title": "Inscriptions from the Stele of Mount Yi",
        "country": "China",
        "culture": "China",
        "image": "https://images.metmuseum.org/CRDImages/as/original/DP-12237-001.jpg"
    },
    {
        "title": "Stele with Figures",
        "country": "China",
        "culture": "China",
        "image": "https://images.metmuseum.org/CRDImages/as/original/43058.jpg"
    },
    {
        "title": "Fragment of a Stele",
        "country": "",
        "culture": "",
        "image": "https://images.metmuseum.org/CRDImages/is/original/08.205.17a.JPG"
    },
    {
        "title": "Fragment of Stele",
        "country": "",
        "culture": "",
        "image": "https://images.metmuseum.org/CRDImages/is/original/10.175.118.JPG"
    },
    {
        "title": "Fragment of Stele",
        "country": "",
        "culture": "",
        "image": "https://images.metmuseum.org/CRDImages/is/original/10.175.121.JPG"
    },
    {
        "title": "Fragments of Stele",
        "country": "",
        "culture": "",
        "image": "https://images.metmuseum.org/CRDImages/is/original/10.175.127.JPG"
    },
    {
        "title": "Fragment of Stele",
        "country": "",
        "culture": "",
        "image": "https://images.metmuseum.org/CRDImages/is/original/10.175.130.JPG"
    },
    {
        "title": "Stele with Vishnu on Garuda",
        "country": "Nepal",
        "culture": "Nepal (Kathmandu Valley)",
        "image": "https://images.metmuseum.org/CRDImages/as/original/67_264_2.JPG"
    },
    {
        "title": "Fragment of Stele",
        "country": "",
        "culture": "",
        "image": "https://images.metmuseum.org/CRDImages/is/original/18.5.3.JPG"
    },
    {
        "title": "Stele with Pure Land Imagery",
        "country": "China",
        "culture": "China",
        "image": "https://images.metmuseum.org/CRDImages/as/original/DP222960.jpg"
    },
    {
        "title": "Section of a Pagoda-Shaped Stele",
        "country": "",
        "culture": "China",
        "image": "https://images.metmuseum.org/CRDImages/as/original/DP163978.jpg"
    },
    {
        "title": "Votive or funerary stele",
        "country": "",
        "culture": "",
        "image": "https://images.metmuseum.org/CRDImages/an/original/DT959.jpg"
    },
    {
        "title": "Stele with Scenes from the Life of the Buddha",
        "country": "Burma",
        "culture": "Burma",
        "image": "https://images.metmuseum.org/CRDImages/as/original/DP701407.jpg"
    },
    {
        "title": "Fragment of a Small Stele",
        "country": "India",
        "culture": "India (Jammu & Kashmir, ancient kingdom of Kashmir)",
        "image": "https://images.metmuseum.org/CRDImages/as/original/1987_142_305.jpg"
    },
    {
        "title": "Rubbings of Yishan stele",
        "country": "China",
        "culture": "China",
        "image": "https://images.metmuseum.org/CRDImages/as/original/1977_375_5_label_strip_sf.jpg"
    },
    {
        "title": "Limestone grave stele of Sogenes",
        "country": "",
        "culture": "Greece, Cypriot",
        "image": "https://images.metmuseum.org/CRDImages/gr/original/DP200690.jpg"
    },
    {
        "title": "Votive Stele with Buddha and Bodhisattvas",
        "country": "",
        "culture": "China",
        "image": "https://images.metmuseum.org/CRDImages/as/original/DP164057.jpg"
    },
    {
        "title": "Stele for the Confucius Temple",
        "country": "",
        "culture": "China",
        "image": "https://images.metmuseum.org/CRDImages/as/original/LC-1977_375_12_at-001.jpg"
    },
    {
        "title": "Stele from the Kerameikos Cemetery, Athens",
        "country": "American",
        "culture": "",
        "image": "https://images.metmuseum.org/CRDImages/ph/original/DP-17643-023.jpg"
    },
    {
        "title": "Sketch of Grave Stele (from Sketchbook)",
        "country": "America",
        "culture": "American",
        "image": "https://images.metmuseum.org/CRDImages/ad/original/219374.jpg"
    },
    {
        "title": "Fragment of a grave stele",
        "country": "",
        "culture": "",
        "image": "https://images.metmuseum.org/CRDImages/an/original/frieze.jpg"
    },
    {
        "title": "Haematite intaglio: Youth on inscribed stele",
        "country": "Italy",
        "culture": "Roman",
        "image": "https://images.metmuseum.org/CRDImages/gr/original/DP277828.jpg"
    },
    {
        "title": "Stele from the Kerameikos Cemetery, Athens",
        "country": "American",
        "culture": "",
        "image": "https://images.metmuseum.org/CRDImages/ph/original/DP-17643-025.jpg"
    },
    {
        "title": "Limestone funerary stele with two recumbent sphinxes",
        "country": "",
        "culture": "Cypriot",
        "image": "https://images.metmuseum.org/CRDImages/gr/original/DP212775.jpg"
    },
    {
        "title": "Stele Compiled by the Monk Daya",
        "country": "",
        "culture": "China",
        "image": "https://images.metmuseum.org/CRDImages/as/original/LC-1977_375_11_at-001.jpg"
    },
    {
        "title": "Rubbing of the Back of theTrübner Stele (29.72)",
        "country": "",
        "culture": "China",
        "image": "https://images.metmuseum.org/CRDImages/as/original/DP216308.jpg"
    },
    {
        "title": "Limestone funerary stele of a boy",
        "country": "",
        "culture": "Cypriot",
        "image": "https://images.metmuseum.org/CRDImages/gr/original/DP212763.jpg"
    },
    {
        "title": "Limestone funerary stele with banquet scene",
        "country": "Italy",
        "culture": "Roman, Cypriot",
        "image": "https://images.metmuseum.org/CRDImages/gr/original/DP218562.jpg"
    },
    {
        "title": "Limestone finial of a funerary stele",
        "country": "",
        "culture": "Cypriot",
        "image": "https://images.metmuseum.org/CRDImages/gr/original/DP210405.jpg"
    },
    {
        "title": "Limestone finial of a funerary stele with two recumbent lions",
        "country": "",
        "culture": "Cypriot",
        "image": "https://images.metmuseum.org/CRDImages/gr/original/DP210411.jpg"
    },
    {
        "title": "Fragment of a limestone funerary stele with a disk and a crescent",
        "country": "",
        "culture": "Cypriot",
        "image": "https://images.metmuseum.org/CRDImages/gr/original/DP212774.jpg"
    },
    {
        "title": "Limestone finial of a funerary stele with two seated lions",
        "country": "",
        "culture": "Cypriot",
        "image": "https://images.metmuseum.org/CRDImages/gr/original/DP229733.jpg"
    },
    {
        "title": "Note on the Back of the Stele for the Monk Yifu",
        "country": "",
        "culture": "China",
        "image": "https://images.metmuseum.org/CRDImages/as/original/LC-1977_375_24_at-001.jpg"
    },
    {
        "title": "Limestone funerary stele with volutes and a Hathor head",
        "country": "",
        "culture": "Cypriot",
        "image": "https://images.metmuseum.org/CRDImages/gr/original/DP212822.jpg"
    },
    {
        "title": "Stele for the Duobao Pagoda of the Qianfusi, in Shensi",
        "country": "",
        "culture": "China",
        "image": "https://images.metmuseum.org/CRDImages/as/original/LC-1977_375_13_at-001.jpg"
    },
    {
        "title": "Limestone finial of a funerary stele with volutes and the head of Hathor",
        "country": "",
        "culture": "Cypriot",
        "image": "https://images.metmuseum.org/CRDImages/gr/original/DP212764.jpg"
    },
    {
        "title": "Stele for the \"Spirit Road\" (leading to the tomb of) Feng Su",
        "country": "",
        "culture": "China",
        "image": "https://images.metmuseum.org/CRDImages/as/original/1977_375_19_label_strip_sf.jpg"
    },
    {
        "title": "Limestone head of a bearded man from a funerary stele",
        "country": "",
        "culture": "Cypriot",
        "image": "https://images.metmuseum.org/CRDImages/gr/original/DP165217.jpg"
    },
    {
        "title": "Fragment of a limestone funerary stele with a seated sphinx",
        "country": "",
        "culture": "Cypriot",
        "image": "https://images.metmuseum.org/CRDImages/gr/original/DP148314.jpg"
    },
    {
        "title": "Limestone head of a lion from a votive stele (?)",
        "country": "",
        "culture": "Cypriot",
        "image": "https://images.metmuseum.org/CRDImages/gr/original/DP158148.jpg"
    },
    {
        "title": "Limestone head of a lion from a votive stele (?)",
        "country": "",
        "culture": "Cypriot",
        "image": "https://images.metmuseum.org/CRDImages/gr/original/DP158512.jpg"
    },
    {
        "title": "Fragment of a limestone funerary stele with a recumbent lion",
        "country": "",
        "culture": "Cypriot",
        "image": "https://images.metmuseum.org/CRDImages/gr/original/DP210501.jpg"
    },
    {
        "title": "Limestone finial of a funerary stele with a seated lion",
        "country": "",
        "culture": "Cypriot",
        "image": "https://images.metmuseum.org/CRDImages/gr/original/DP210980.jpg"
    },
    {
        "title": "Limestone finial of a funerary stele with a recumbent lion and a banquet scene",
        "country": "",
        "culture": "Cypriot",
        "image": "https://images.metmuseum.org/CRDImages/gr/original/DP212771.jpg"
    },
    {
        "title": "List of Censors, engraved on the back of the Stele for Yushitai Jingshe (1977.375.26)",
        "country": "",
        "culture": "China",
        "image": "https://images.metmuseum.org/CRDImages/as/original/LC-1977_375_27_at-001.jpg"
    },
    {
        "title": "Limestone finial of a funerary stele with a recumbent lion and a banquet scene",
        "country": "",
        "culture": "Cypriot",
        "image": "https://images.metmuseum.org/CRDImages/gr/original/DP212772.jpg"
    },
    {
        "title": "Limestone finial of a votive stele (?) with a lion and a male sphinx",
        "country": "",
        "culture": "Cypriot",
        "image": "https://images.metmuseum.org/CRDImages/gr/original/DP263906.jpg"
    },
    {
        "title": "Djébel Selséleh (Silsilis), Steles Architecturales Taillées Dans les Carriéres",
        "country": "French",
        "culture": "",
        "image": "https://images.metmuseum.org/CRDImages/ph/original/DP138589.jpg"
    },
    {
        "title": "Flying Apsaras (Hiten)",
        "country": "",
        "culture": "Japan",
        "image": "https://images.metmuseum.org/CRDImages/as/original/2015_300_251a_Burke_website.jpg"
    },
    {
        "title": "Male and Female Shinto Deities",
        "country": "",
        "culture": "Japan",
        "image": "https://images.metmuseum.org/CRDImages/as/original/DP-16151-001.jpg"
    },
    {
        "title": "Fudō Myōō",
        "country": "",
        "culture": "Japan",
        "image": "https://images.metmuseum.org/CRDImages/as/original/DP356182.jpg"
    },
    {
        "title": "Dainichi Nyorai",
        "country": "",
        "culture": "Japan",
        "image": "https://images.metmuseum.org/CRDImages/as/original/DP233932.jpg"
    },
    {
        "title": "Jizō Bosatsu",
        "country": "",
        "culture": "Japan",
        "image": "https://images.metmuseum.org/CRDImages/as/original/DP-15581-060.jpg"
    },
    {
        "title": "Bodhisattva with Crossed Ankles",
        "country": "",
        "culture": "China",
        "image": "https://images.metmuseum.org/CRDImages/as/original/DP170267.jpg"
    },
    {
        "title": "Amida Nyorai",
        "country": "",
        "culture": "Japan",
        "image": "https://images.metmuseum.org/CRDImages/as/original/DP-15581-064.jpg"
    },
    {
        "title": "Eleven-Headed Kannon",
        "country": "",
        "culture": "Japan",
        "image": "https://images.metmuseum.org/CRDImages/as/original/DT289463.jpg"
    },
    {
        "title": "Wayfarers Looking at the Statue of Jizo Bosatsu in a Pine Grove at Hashiba",
        "country": "Japanese",
        "culture": "Japan",
        "image": "https://images.metmuseum.org/CRDImages/as/original/DP124466.jpg"
    },
    {
        "title": "Guardian King of the Four Directions",
        "country": "",
        "culture": "Japan",
        "image": "https://images.metmuseum.org/CRDImages/as/original/DP235251.jpg"
    },
    {
        "title": "Portable Shrine with the Horse-Headed Kannon",
        "country": "",
        "culture": "Japan",
        "image": "https://images.metmuseum.org/CRDImages/as/original/DT8063.jpg"
    },
    {
        "title": "Guardian King of the Four Directions",
        "country": "",
        "culture": "Japan",
        "image": "https://images.metmuseum.org/CRDImages/as/original/DP233934.jpg"
    },
    {
        "title": "Fudō Myōō (Achala-vidyārāja)",
        "country": "",
        "culture": "Japan",
        "image": "https://images.metmuseum.org/CRDImages/as/original/DT223.jpg"
    },
    {
        "title": "Statue of the Bodhisattva Fugen (Fugenzō)",
        "country": "Japanese",
        "culture": "Japan",
        "image": "https://images.metmuseum.org/CRDImages/as/original/JIB49_006_crd.jpg"
    },
    {
        "title": "Prince Shotoku at Age Sixteen",
        "country": "",
        "culture": "Japan",
        "image": "https://images.metmuseum.org/CRDImages/as/original/DP231449.jpg"
    },
    {
        "title": "Zaō Gongen",
        "country": "",
        "culture": "Japan",
        "image": "https://images.metmuseum.org/CRDImages/as/original/DT5160.jpg"
    },
    {
        "title": "Finial of a Buddhist Monk’s Staff (Shakujō)",
        "country": "",
        "culture": "Japan",
        "image": "https://images.metmuseum.org/CRDImages/as/original/867.jpg"
    },
    {
        "title": "Fudō Myōō",
        "country": "",
        "culture": "Japan",
        "image": "https://images.metmuseum.org/CRDImages/as/original/DP-12551-001.jpg"
    },
    {
        "title": "The Collector of Prints",
        "country": "French",
        "culture": "",
        "image": "https://images.metmuseum.org/CRDImages/ep/original/DT1920.jpg"
    },
    {
        "title": "Fishing Boats with Nets under Ryōgoku Bridge",
        "country": "Japanese",
        "culture": "Japan",
        "image": "https://images.metmuseum.org/CRDImages/as/original/DP151604.jpg"
    },
    {
        "title": "Fudō Myōō Threatening a Novice",
        "country": "Japanese",
        "culture": "Japan",
        "image": "https://images.metmuseum.org/CRDImages/as/original/DP147713.jpg"
    },
    {
        "title": "Rakan",
        "country": "Japanese",
        "culture": "Japan",
        "image": "https://images.metmuseum.org/CRDImages/as/original/DT242491.jpg"
    },
    {
        "title": "Fudō Myōō in Portable Shrine",
        "country": "Japan",
        "culture": "Japan",
        "image": "https://images.metmuseum.org/CRDImages/as/original/DP372023.jpg"
    },
    {
        "title": "Landscape after Xia Gui",
        "country": "Japan",
        "culture": "Japan",
        "image": "https://images.metmuseum.org/CRDImages/as/original/DP704892.jpg"
    },
    {
        "title": "Eight Attendants of Fudō Myōō",
        "country": "Japan",
        "culture": "Japan",
        "image": "https://images.metmuseum.org/CRDImages/as/original/67_55_38_O1.jpg"
    },
    {
        "title": "Fudō Myōō with Four Attendants, Outlined in Seed Syllables",
        "country": "Japan",
        "culture": "Japan",
        "image": "https://images.metmuseum.org/CRDImages/as/original/DP357988.jpg"
    },
    {
        "title": "Amida Nyorai",
        "country": "Japan",
        "culture": "Japan",
        "image": "https://images.metmuseum.org/CRDImages/as/original/1975_268_168_207080.jpg"
    },
    {
        "title": "Zen Master with Meditation Staff, and Chinese-Style Landscapes",
        "country": "Japan",
        "culture": "Japan",
        "image": "https://images.metmuseum.org/CRDImages/as/original/DP-14063-001.jpg"
    },
    {
        "title": "Priest in Meditation",
        "country": "Japan",
        "culture": "Japan",
        "image": "https://images.metmuseum.org/CRDImages/as/original/DP-12380-002.jpg"
    },
    {
        "title": "Kongō-hō Bosatsu (Vajrasattva)",
        "country": "Japan",
        "culture": "Japan",
        "image": "https://images.metmuseum.org/CRDImages/as/original/1975_268_154_F.JPG"
    },
    {
        "title": "Tobatsu Bishamonten",
        "country": "Japan",
        "culture": "Japan",
        "image": "https://images.metmuseum.org/CRDImages/as/original/2015_300_253ab_Burke_website.jpg"
    },
    {
        "title": "Hiten",
        "country": "Japan",
        "culture": "Japan",
        "image": "https://images.metmuseum.org/CRDImages/as/original/2002_447_3.jpg"
    },
    {
        "title": "Attendant Bodhisattva Seishi",
        "country": "Japan",
        "culture": "Japan",
        "image": "https://images.metmuseum.org/CRDImages/as/original/13981.jpg"
    },
    {
        "title": "Seated Buddha",
        "country": "Japan",
        "culture": "Japan",
        "image": "https://images.metmuseum.org/CRDImages/as/original/1975_268_153_F1_sf.JPG"
    },
    {
        "title": "Bishamonten",
        "country": "Japan",
        "culture": "Japan",
        "image": "https://images.metmuseum.org/CRDImages/as/original/DP142111.jpg"
    },
    {
        "title": "Statuette of Buddha Sitting on Engraved Throne",
        "country": "Korea",
        "culture": "Korea",
        "image": "https://images.metmuseum.org/CRDImages/as/original/17_118_49_36907.jpg"
    },
    {
        "title": "Shandao",
        "country": "Japan",
        "culture": "Japan",
        "image": "https://images.metmuseum.org/CRDImages/as/original/DP231452.jpg"
    },
    {
        "title": "Dogū (Clay Figurine)",
        "country": "Japan",
        "culture": "Japan",
        "image": "https://images.metmuseum.org/CRDImages/as/original/DP246469.jpg"
    },
    {
        "title": "Hōnen",
        "country": "Japan",
        "culture": "Japan",
        "image": "https://images.metmuseum.org/CRDImages/as/original/DP231445.jpg"
    },
    {
        "title": "Clay Relief Tile with Buddhist Triad (Sanzon senbutsu)",
        "country": "Japan",
        "culture": "Japan",
        "image": "https://images.metmuseum.org/CRDImages/as/original/2015_300_249_F_Burke.jpg"
    },
    {
        "title": "Dogū (Clay Figurine)",
        "country": "Japan",
        "culture": "Japan",
        "image": "https://images.metmuseum.org/CRDImages/as/original/DT10152.jpg"
    },
    {
        "title": "Aizen Mandala",
        "country": "Japan",
        "culture": "Japan",
        "image": "https://images.metmuseum.org/CRDImages/as/original/DP-12232-002.jpg"
    },
    {
        "title": "Mandala of Wakamiya of Kasuga Shrine (Kasuga wakamiya mandara)",
        "country": "Japan",
        "culture": "Japan",
        "image": "https://images.metmuseum.org/CRDImages/as/original/DT374578.jpg"
    },
    {
        "title": "Dogū (Clay Figurine)",
        "country": "Japan",
        "culture": "Japan",
        "image": "https://images.metmuseum.org/CRDImages/as/original/DT10516.jpg"
    }

]
    
}